accelbyte_py_sdk/api/social/__init__.py
accelbyte_py_sdk/api/social/errors.py
accelbyte_py_sdk/api/social/models/__init__.py
accelbyte_py_sdk/api/social/models/a_dto_object_for_resetting_user_stat_items.py
accelbyte_py_sdk/api/social/models/a_dto_object_for_user_stat_item_value.py
accelbyte_py_sdk/api/social/models/attribute.py
accelbyte_py_sdk/api/social/models/bulk_cycle_stats_add.py
accelbyte_py_sdk/api/social/models/bulk_stat_cycle_operation_result.py
accelbyte_py_sdk/api/social/models/bulk_stat_cycle_request.py
accelbyte_py_sdk/api/social/models/bulk_stat_cycle_result.py
accelbyte_py_sdk/api/social/models/bulk_stat_item_create.py
accelbyte_py_sdk/api/social/models/bulk_stat_item_inc.py
accelbyte_py_sdk/api/social/models/bulk_stat_item_reset.py
accelbyte_py_sdk/api/social/models/bulk_stat_item_update.py
accelbyte_py_sdk/api/social/models/bulk_stat_operation_result.py
accelbyte_py_sdk/api/social/models/bulk_user_stat_item_by_stat_codes.py
accelbyte_py_sdk/api/social/models/bulk_user_stat_item_inc.py
accelbyte_py_sdk/api/social/models/bulk_user_stat_item_reset.py
accelbyte_py_sdk/api/social/models/bulk_user_stat_item_update.py
accelbyte_py_sdk/api/social/models/cycle_override.py
accelbyte_py_sdk/api/social/models/cycle_override_request.py
accelbyte_py_sdk/api/social/models/error_entity.py
accelbyte_py_sdk/api/social/models/field_validation_error.py
accelbyte_py_sdk/api/social/models/game_profile_header.py
accelbyte_py_sdk/api/social/models/game_profile_info.py
accelbyte_py_sdk/api/social/models/game_profile_public_info.py
accelbyte_py_sdk/api/social/models/game_profile_request.py
accelbyte_py_sdk/api/social/models/global_stat_item_info.py
accelbyte_py_sdk/api/social/models/global_stat_item_paging_sliced_result.py
accelbyte_py_sdk/api/social/models/namespace_slot_config_info.py
accelbyte_py_sdk/api/social/models/paging.py
accelbyte_py_sdk/api/social/models/permission.py
accelbyte_py_sdk/api/social/models/slot_config_update.py
accelbyte_py_sdk_service_social-0.26.0.dist-info/METADATA
accelbyte_py_sdk_service_social-0.26.0.dist-info/WHEEL
accelbyte_py_sdk_service_social-0.26.0.dist-info/top_level.txt
accelbyte_py_sdk_service_social-0.26.0.dist-info/RECORD
